devops_runner_python/__init__.py
devops_runner_python/discovery.py
devops_runner_python/env.py
devops_runner_python/env_validation.py
devops_runner_python/pyproject.py
devops_runner_python/cli/__init__.py
devops_runner_python/cli/exec.py
devops_runner_python/cli/run.py
devops_runner_python/cli/run_many.py
devops_runner_python/cli/uv.py
devops_runner_python-0.1.14.dist-info/METADATA
devops_runner_python-0.1.14.dist-info/WHEEL
devops_runner_python-0.1.14.dist-info/entry_points.txt
devops_runner_python-0.1.14.dist-info/RECORD
