Metadata-Version: 2.4
Name: devops-runner-python
Version: 0.1.14
Project-URL: Homepage, https://github.com/vaharoni/devops-python
Project-URL: Issues, https://github.com/vaharoni/devops-python/issues
Author-email: Amit Aharoni <amit.sites@gmail.com>
Requires-Python: >=3.12
Requires-Dist: colorama<0.5.0,>=0.4.6
Requires-Dist: pydantic<3.0.0,>=2.10.6
Requires-Dist: python-dotenv<2.0.0,>=1.0.1
Requires-Dist: pyyaml<7.0.0,>=6.0.2
Requires-Dist: tomli<3.0.0,>=2.2.1
